mase/DataSimulation.py
mase/__init__.py
mase/demo.py
mase-0.0.7.dist-info/LICENSE
mase-0.0.7.dist-info/METADATA
mase-0.0.7.dist-info/WHEEL
mase-0.0.7.dist-info/top_level.txt
mase-0.0.7.dist-info/RECORD
