Metadata-Version: 2.1
Name: mase
Version: 0.0.7
Summary: A data simulation engine for multivariate time series data.
Home-page: https://github.com/Marco-Christiani/MASE
Author: Marco Christiani
Author-email: mchristiani2017@gmail.com
License: UNKNOWN
Platform: UNKNOWN
Classifier: Programming Language :: Python :: 3
Classifier: License :: OSI Approved :: GNU General Public License v3 (GPLv3)
Classifier: Operating System :: OS Independent
Requires-Python: >=3.6
Requires-Dist: numpy
Requires-Dist: pandas
Requires-Dist: matplotlib
Requires-Dist: pyplot-themes
Requires-Dist: seaborn
